{
  "generated_at": "2026-04-28T22:57:24Z",
  "ranking": [
    { "position": 1, "player": "TNT", "chests": 177 },
    { "position": 2, "player": "Starmoon", "chests": 145 },
    { "position": 3, "player": "Peluca", "chests": 91 },
    { "position": 4, "player": "Arya", "chests": 88 },
    { "position": 5, "player": "Cris", "chests": 82 },
    { "position": 6, "player": "KIKING", "chests": 81 },
    { "position": 7, "player": "Faz", "chests": 74 },
    { "position": 8, "player": "semnethai", "chests": 73 },
    { "position": 9, "player": "Elizabeth", "chests": 65 },
    { "position": 10, "player": "SHIVA", "chests": 55 },
    { "position": 11, "player": "Fin", "chests": 55 },
    { "position": 12, "player": "Gavidwyn", "chests": 54 },
    { "position": 13, "player": "Eyrodor", "chests": 54 },
    { "position": 14, "player": "Bernoden", "chests": 54 },
    { "position": 15, "player": "Periel", "chests": 51 },
    { "position": 16, "player": "Fobur", "chests": 47 },
    { "position": 17, "player": "Tamim", "chests": 46 },
    { "position": 18, "player": "MDrudi", "chests": 45 },
    { "position": 19, "player": "Orodgon", "chests": 43 },
    { "position": 20, "player": "what an awesome GOD", "chests": 40 },
    { "position": 21, "player": "Globetrotter", "chests": 40 },
    { "position": 22, "player": "rosa", "chests": 38 },
    { "position": 23, "player": "Moogujora", "chests": 38 },
    { "position": 24, "player": "Eyien", "chests": 38 },
    { "position": 25, "player": "sandra", "chests": 37 },
    { "position": 26, "player": "DARKSIDE", "chests": 36 },
    { "position": 27, "player": "OnYxMoOr", "chests": 35 },
    { "position": 28, "player": "CRAZYHORSE II", "chests": 35 },
    { "position": 29, "player": "Jujinn", "chests": 33 },
    { "position": 30, "player": "Carbayu", "chests": 33 },
    { "position": 31, "player": "MIKE", "chests": 32 },
    { "position": 32, "player": "Kagamand", "chests": 31 },
    { "position": 33, "player": "Finros SK3", "chests": 31 },
    { "position": 34, "player": "DT KC 58", "chests": 31 },
    { "position": 35, "player": "ronaldlion", "chests": 30 },
    { "position": 36, "player": "Ariron", "chests": 30 },
    { "position": 37, "player": "Hengist the Wake", "chests": 27 },
    { "position": 38, "player": "Nissa Ran", "chests": 26 },
    { "position": 39, "player": "Nighty WarLord", "chests": 26 },
    { "position": 40, "player": "Landis", "chests": 25 },
    { "position": 41, "player": "Fandisilas", "chests": 25 },
    { "position": 42, "player": "Nayem 3", "chests": 24 },
    { "position": 43, "player": "Fallegin", "chests": 24 },
    { "position": 44, "player": "Aremorica", "chests": 24 },
    { "position": 45, "player": "Garon", "chests": 23 },
    { "position": 46, "player": "Fabi sk", "chests": 22 },
    { "position": 47, "player": "zuntezu", "chests": 21 },
    { "position": 48, "player": "Raider CP", "chests": 21 },
    { "position": 49, "player": "Finros SK4", "chests": 21 },
    { "position": 50, "player": "XI VICTOR IX", "chests": 20 },
    { "position": 51, "player": "Dujas", "chests": 20 },
    { "position": 52, "player": "Elinor", "chests": 19 },
    { "position": 53, "player": "SK QAISER", "chests": 18 },
    { "position": 54, "player": "Lavianu", "chests": 18 },
    { "position": 55, "player": "lanzius", "chests": 18 },
    { "position": 56, "player": "Akile", "chests": 18 },
    { "position": 57, "player": "FODAO", "chests": 17 },
    { "position": 58, "player": "Sung Jinwoo", "chests": 16 },
    { "position": 59, "player": "Tkhonrad", "chests": 15 },
    { "position": 60, "player": "Larrining SK", "chests": 15 },
    { "position": 61, "player": "Agamaginn", "chests": 15 },
    { "position": 62, "player": "sabri ctz", "chests": 14 },
    { "position": 63, "player": "Méraz", "chests": 13 },
    { "position": 64, "player": "Angry Nimue", "chests": 13 },
    { "position": 65, "player": "Felor", "chests": 11 },
    { "position": 66, "player": "Wrathfont", "chests": 10 },
    { "position": 67, "player": "Nijurus", "chests": 9 },
    { "position": 68, "player": "Elfiren", "chests": 9 },
    { "position": 69, "player": "Derrinen", "chests": 8 },
    { "position": 70, "player": "Free Hel", "chests": 6 },
    { "position": 71, "player": "Eyanin", "chests": 6 },
    { "position": 72, "player": "Douran", "chests": 6 },
    { "position": 73, "player": "David", "chests": 6 },
    { "position": 74, "player": "Corona Mex", "chests": 6 },
    { "position": 75, "player": "Frankdrovard", "chests": 5 },
    { "position": 76, "player": "Crocodile Doneknee3", "chests": 4 },
    { "position": 77, "player": "Tygonris", "chests": 1 },
    { "position": 78, "player": "ATeeF", "chests": 1 }
  ]
}
