{
  "generated_at": "2026-05-31T17:56:33Z",
  "ranking": [
    { "position": 1, "player": "Starmoon", "chests": 381 },
    { "position": 2, "player": "Dujas", "chests": 235 },
    { "position": 3, "player": "KIKING", "chests": 202 },
    { "position": 4, "player": "CRAZYHORSE II", "chests": 171 },
    { "position": 5, "player": "SHIVA", "chests": 152 },
    { "position": 6, "player": "Cris", "chests": 151 },
    { "position": 7, "player": "Faz", "chests": 138 },
    { "position": 8, "player": "Elizabeth", "chests": 135 },
    { "position": 9, "player": "Fabi sk", "chests": 133 },
    { "position": 10, "player": "Bośka", "chests": 132 },
    { "position": 11, "player": "TNT", "chests": 124 },
    { "position": 12, "player": "DT KC 58", "chests": 123 },
    { "position": 13, "player": "rosa", "chests": 120 },
    { "position": 14, "player": "OnYxMoOr", "chests": 118 },
    { "position": 15, "player": "Eyrodor", "chests": 114 },
    { "position": 16, "player": "Arrining", "chests": 114 },
    { "position": 17, "player": "Akile", "chests": 103 },
    { "position": 18, "player": "Kam972", "chests": 101 },
    { "position": 19, "player": "MDrudi", "chests": 98 },
    { "position": 20, "player": "Corona Mex", "chests": 98 },
    { "position": 21, "player": "Ariron", "chests": 95 },
    { "position": 22, "player": "Ares", "chests": 95 },
    { "position": 23, "player": "Periel", "chests": 93 },
    { "position": 24, "player": "Elfiren", "chests": 92 },
    { "position": 25, "player": "VoLKaN", "chests": 91 },
    { "position": 26, "player": "Gavidwyn", "chests": 91 },
    { "position": 27, "player": "Fin", "chests": 91 },
    { "position": 28, "player": "Fandisilas", "chests": 91 },
    { "position": 29, "player": "Aremorica", "chests": 89 },
    { "position": 30, "player": "Sung Jinwoo", "chests": 85 },
    { "position": 31, "player": "DARKSIDE", "chests": 85 },
    { "position": 32, "player": "Railan", "chests": 84 },
    { "position": 33, "player": "what an awesome GOD", "chests": 83 },
    { "position": 34, "player": "Ottoman military", "chests": 81 },
    { "position": 35, "player": "Fobur", "chests": 81 },
    { "position": 36, "player": "Peluca", "chests": 80 },
    { "position": 37, "player": "Nissa Ran", "chests": 80 },
    { "position": 38, "player": "Kagamand", "chests": 79 },
    { "position": 39, "player": "Kam ABC", "chests": 77 },
    { "position": 40, "player": "Carbayu", "chests": 77 },
    { "position": 41, "player": "SABRINA", "chests": 74 },
    { "position": 42, "player": "Hengist the Wake", "chests": 74 },
    { "position": 43, "player": "FODAO", "chests": 74 },
    { "position": 44, "player": "SK QAISER", "chests": 73 },
    { "position": 45, "player": "PhredToo", "chests": 73 },
    { "position": 46, "player": "Bernoden", "chests": 67 },
    { "position": 47, "player": "Nijurus", "chests": 58 },
    { "position": 48, "player": "Stoner94", "chests": 57 },
    { "position": 49, "player": "lanzius", "chests": 57 },
    { "position": 50, "player": "Crocodile Doneknee3", "chests": 54 },
    { "position": 51, "player": "Garon", "chests": 50 },
    { "position": 52, "player": "Jujinn", "chests": 49 },
    { "position": 53, "player": "Moogujora", "chests": 48 },
    { "position": 54, "player": "Derrinen", "chests": 47 },
    { "position": 55, "player": "Agamaginn", "chests": 47 },
    { "position": 56, "player": "Finros SK3", "chests": 44 },
    { "position": 57, "player": "Larrining SK", "chests": 42 },
    { "position": 58, "player": "Nighty WarLord", "chests": 39 },
    { "position": 59, "player": "MIKE", "chests": 38 },
    { "position": 60, "player": "valkillrie", "chests": 35 },
    { "position": 61, "player": "sandra", "chests": 33 },
    { "position": 62, "player": "Elinor", "chests": 33 },
    { "position": 63, "player": "Khonsu", "chests": 32 },
    { "position": 64, "player": "Nayem 3", "chests": 31 },
    { "position": 65, "player": "Kambrick", "chests": 31 },
    { "position": 66, "player": "Aiza", "chests": 29 },
    { "position": 67, "player": "Finros SK4", "chests": 28 },
    { "position": 68, "player": "Free Hel", "chests": 27 },
    { "position": 69, "player": "Catalonia", "chests": 23 },
    { "position": 70, "player": "Servenel", "chests": 22 },
    { "position": 71, "player": "Frankdrovard", "chests": 21 },
    { "position": 72, "player": "Fallegin", "chests": 21 },
    { "position": 73, "player": "Escape", "chests": 21 },
    { "position": 74, "player": "ATeeF", "chests": 20 },
    { "position": 75, "player": "King Frizzo", "chests": 16 },
    { "position": 76, "player": "Tkhonrad", "chests": 13 },
    { "position": 77, "player": "team 1 galadriel", "chests": 13 },
    { "position": 78, "player": "Douran", "chests": 13 },
    { "position": 79, "player": "Jasper", "chests": 12 },
    { "position": 80, "player": "Raider CP", "chests": 11 },
    { "position": 81, "player": "David", "chests": 11 },
    { "position": 82, "player": "zuntezu", "chests": 10 },
    { "position": 83, "player": "Börtecine", "chests": 9 },
    { "position": 84, "player": "Eyien", "chests": 8 },
    { "position": 85, "player": "Eyanin", "chests": 8 },
    { "position": 86, "player": "Lavianu", "chests": 5 },
    { "position": 87, "player": "XI VICTOR IX", "chests": 4 },
    { "position": 88, "player": "Wrathfont", "chests": 4 },
    { "position": 89, "player": "Tygonris", "chests": 3 },
    { "position": 90, "player": "sabri ctz", "chests": 2 },
    { "position": 91, "player": "Moira", "chests": 2 }
  ]
}
